Workbook

Sheet 1_Bilan_source
A1: Compte | B1: Montant_MEUR | C1: Type_Info | D1: Commentaire
A2: Credits Grandes Entreprises | B2: 550 | C2: Actif | D2: les 55% du bilan
A3: Credits PME Retail | B3: 50 | C3: Actif | D3: Les petits pros
A4: Credits Immobiliers | B4: 300 | C4: Actif | D4: Hypothèques
A5: Titres Souverains | B5: 50 | C5: Actif | D5: Bons du trésor
A6: Tresorerie Cash | B6: 50 | C6: Actif | D6: Cash BCE
A7: TOTAL ACTIF COMPTABLE | B7: =SUM(B2:B6) -> 1000
A8: Capitaux Propres | B8: 85 | C8: Passif | D8: Ton Capital
A9: Goodwill | B9: 5 | C9: Deduction | D9: À déduire
A10: PNB Moyen 3ans | B10: 40 | C10: Compte de résultat | D10: Pour le Risque Op.
A11: Provisions Actuelles | B11: 15 | C11: Risque | D11: Stock actuel

Sheet 2_Mapping
A1: Ligne_Bilan | B1: Exposition_MEUR | C1: Classe_Actif_CRR | D1: RW_Standard | E1: Commentaire
A2: Credits Grandes Entreprises | B2: ='1_Bilan_source'!B2 -> 550 | C2: Corporate | D2: 1 | E2: Non noté (Art 122)
A3: Credits PME Retail | B3: ='1_Bilan_source'!B3 -> 50 | C3: Retail SME | D3: 0.75 | E3: Granularité (Art 123)
A4: Credits Immobiliers | B4: ='1_Bilan_source'!B4 -> 300 | C4: Secured Mortgage | D4: 0.35 | E4: Garanti (Art 125)
A5: Titres Souverains | B5: ='1_Bilan_source'!B5 -> 50 | C5: Sovereign | D5: 0 | E5: État UE (Art 114)
A6: Tresorerie Cash | B6: ='1_Bilan_source'!B6 -> 50 | C6: Central Bank | D6: 0 | E6: Sans risque

Sheet 3_RWA_Calculs
A1: Classe_Exposition | B1: EAD_MEUR | C1: Ponderation_Risque | D1: RWA_MEUR | E1: Commentaire
A2: Corporate GE | B2: ='2_Mapping'!B2 -> 550 | C2: ='2_Mapping'!D2 -> 1 | D2: =B2*C2 -> 550 | E2: Grandes entreprises
A3: PME Retail | B3: ='2_Mapping'!B3 -> 50 | C3: ='2_Mapping'!D3 -> 0.75 | D3: =B3*C3 -> 37.5 | E3: PME éligibles retail
A4: Immobilier Retail | B4: ='2_Mapping'!B4 -> 300 | C4: ='2_Mapping'!D4 -> 0.35 | D4: =B4*C4 -> 105 | E4: Prêts immobiliers
A5: Souverain Cash | B5: ='2_Mapping'!B5 -> 50 | C5: 0 | D5: =B5*C5 -> 0 | E5: Etats & cash (Regroupés)
A6: TOTAL_RWA CREDIT | D6: =SUM(D2:D5) -> 692.5 | E6: Sous-total Crédit
A8: RISQUE OPERATIONNEL | B8: Base Calcul | C8: Facteur BIA | D8: RWA Op | E8: Indispensable pour Onglet 4
A9: Op Risk BIA | B9: ='1_Bilan_source'!B10 -> 40 | C9: 1.875 | D9: =B9*C9 -> 75 | E9: Méthode BIA
A11: TOTAL RWA GLOBAL | D11: =D6+D9 -> 767.5 | E11: Total pour Ratio

Sheet 4_Ratio_CET1
A1: Element | B1: Montant_MEUR | C1: Commentaire
A2: Capitaux Propres Comptables | B2: ='1_Bilan_source'!B8 -> 85 | C2: Capital + réserves
A3: (-)_Goodwill | B3: =-'1_Bilan_source'!B9 -> -5 | C3: Déduction prudentielle CRR
A4: CET1 Prudentiel | B4: =SUM(B2:B3) -> 80 | C4: Numérateur CET1
A5: TOTAL RWA | B5: ='3_RWA_Calculs'!D11 -> 767.5 | C5: Dénominateur (Crédit + Op)
A6: Ratio CET1 | B6: =B4/B5 -> 0.10423453 | C6: A formater en %

Sheet 5_Stress_Test
A1: Categorie | B1: Choc | C1: Impact_MEUR | D1: Commentaire
A2: CET1 | B2: Hausse Cout du Risque | C2: -25 | D2: Dégradation macro sévère
A3: CET1 | B3: Dotations Supplementaires | C3: -10 | D3: Stress portefeuille crédit
A4: RWA | B4: Inflation RWA Corporate | C4: ='3_RWA_Calculs'!D2*25% -> 137.5 | D4: Proxy RW 125% (+25pts)
A5: RWA | B5: Stress Climatique | C5: 30 | D5: Penalité "Actifs bruns"
A7: RESULTATS STRESS | B7: FORMULE | C7: MONTANT | D7: VERDICT
A8: CET1 Post Stress | B8: Ratio_CET1 +Hausse Cout du Risque + Dotations Supplementaires | C8: ='4_Ratio_CET1'!B4 + SUM(C2:C3) -> 45 | D8: Capital qui reste (Numérateur)
A9: RWA Post Stress | B9: TOTAL RWA+Inflation RWA Corporate + Stress Climatique | C9: ='4_Ratio_CET1'!B5 + SUM(C4:C5) -> 935 | D9: Risque qui gonfle (Dénominateur)
A10: Ratio CET1 Stress | C10: =C8/C9 -> 0.048128342 | D10: Doit être < Ratio Initial

Sheet 6_Waterfalll
A1: Facteur | B1: Impact | C1: Pourcentage | D1: Commentaire / Calcul
A2: Ratio CET1 Initial (T0) | B2: ='4_Ratio_CET1'!B6 -> 0.10423453 | C2: =B2 -> 0.10423453 | D2: Base : 80 M€ / 767,5 M€
A3: Effet Baisse Fonds Propres | B3: =('5_Stress_Test'!C2+'5_Stress_Test'!C3)/'4_Ratio_CET1'!B5 -> -0.045602606 | C3: =B3 -> -0.045602606 | D3: Impact massif car numérateur
A4: dont Coût du Risque (-25 M€) | B4: =B3*('5_Stress_Test'!C2/SUM('5_Stress_Test'!C2:C3)) -> -0.03257329 | C4: =B4 -> -0.03257329
A5: dont Dotations (-10 M€) | B5: =B3*('5_Stress_Test'!C3/SUM('5_Stress_Test'!C2:C3)) -> -0.013029316 | C5: =B5 -> -0.013029316
A6: Effet Hausse des RWA | B6: =('5_Stress_Test'!C8/'5_Stress_Test'!C9)-('5_Stress_Test'!C8/'4_Ratio_CET1'!B5) -> -0.01050358 | C6: =B6 -> -0.01050358 | D6: Impact dilutif sur le capital restant
A7: dont RWA Corporate (+137,5 M€) | B7: =B6*('5_Stress_Test'!C4/SUM('5_Stress_Test'!C4:C5)) -> -0.0086223414 | C7: =B7 -> -0.0086223414
A8: dont Stress Climatique (+30 M€) | B8: =B6*('5_Stress_Test'!C5/SUM('5_Stress_Test'!C4:C5)) -> -0.0018812381 | C8: =B8 -> -0.0018812381
A9: Ratio CET1 Final (Stress) | B9: ='5_Stress_Test'!C10 -> 0.048128342 | C9: =B9 -> 0.048128342 | D9: Base : 45 M€ / 935 M€

Sheet 7_Controles
A1: Controle_Effectue | B1: Valeur_Calculée | C1: Seuil_Attendu | D1: Ecart_Constaté | E1: Statut
A2: Intégrité Bilan | B2: ='1_Bilan_source'!B7 -> 1000 | C2: 1000 | D2: =B2-C2 -> 0 | E2: =IF(ABS(D2)<0.01,"valide","ERREUR") -> valide
A3: Déduction Goodwill | B3: ='4_Ratio_CET1'!B3 -> -5 | C3: <0 | D3: =B3-0 -> -5 | E3: =IF(B3<0,"valide"," ERREUR") -> valide
A4: Densité Risque (RWA%) | B4: ='4_Ratio_CET1'!B5/'1_Bilan_source'!B7 -> 0.7675 | C4: <85% | D4: =B4-85% -> -0.0825 | E4: =IF(B4<C4,"valide","ERREUR") -> valide
A5: Cohérence Stress | B5: ='5_Stress_Test'!C10 -> 0.048128342 | C5: ='4_Ratio_CET1'!B6 -> 0.10423453 | D5: =B5-C5 -> -0.056106185 | E5: =IF(D5<0,"valide","ERREUR") -> valide
A6: Vérif Capital (CET1) | B6: ='4_Ratio_CET1'!B4 -> 80 | C6: 80 | D6: =B6-C6 -> 0 | E6: =IF(D6=0,"valide","ERREUR") -> valide
